eii/__init__.py
eii/exc.py
eii/msg_envelope.cpython-38-x86_64-linux-gnu.so
eii/msgbus.cpython-38-x86_64-linux-gnu.so
eii/publisher.cpython-38-x86_64-linux-gnu.so
eii/receive_context.cpython-38-x86_64-linux-gnu.so
eii/service.cpython-38-x86_64-linux-gnu.so
eii/service_requester.cpython-38-x86_64-linux-gnu.so
eii_messagebus-3.0.dist-info/METADATA
eii_messagebus-3.0.dist-info/WHEEL
eii_messagebus-3.0.dist-info/top_level.txt
eii_messagebus-3.0.dist-info/RECORD
